odoo/addons/pos_cash_control_extension/README.rst
odoo/addons/pos_cash_control_extension/__init__.py
odoo/addons/pos_cash_control_extension/__manifest__.py
odoo/addons/pos_cash_control_extension/i18n/it.po
odoo/addons/pos_cash_control_extension/i18n/pos_cash_control_extension.pot
odoo/addons/pos_cash_control_extension/models/__init__.py
odoo/addons/pos_cash_control_extension/models/pos_session.py
odoo/addons/pos_cash_control_extension/readme/CONTRIBUTORS.md
odoo/addons/pos_cash_control_extension/readme/DESCRIPTION.md
odoo/addons/pos_cash_control_extension/static/description/icon.png
odoo/addons/pos_cash_control_extension/static/description/icon.svg
odoo/addons/pos_cash_control_extension/static/description/index.html
odoo/addons/pos_cash_control_extension/tests/__init__.py
odoo/addons/pos_cash_control_extension/tests/test_cash_control.py
odoo_addon_pos_cash_control_extension-17.0.1.0.0.4.dist-info/METADATA
odoo_addon_pos_cash_control_extension-17.0.1.0.0.4.dist-info/WHEEL
odoo_addon_pos_cash_control_extension-17.0.1.0.0.4.dist-info/top_level.txt
odoo_addon_pos_cash_control_extension-17.0.1.0.0.4.dist-info/RECORD
